{
  "STARTING_CASH_YEN": 300000,
  "WEEKLY_RENT_YEN": 20000,
  "DOUBLE_PARKING_FINE_YEN": 8000,
  "AUCTION_RESERVE_PRICE_FRACTION": 0.6,
  "AUCTION_LOTS_PER_TIER": {
    "local-yard": 3,
    "regional": 3,
    "premium": 2,
    "collector-network": 1
  },
  "AUCTION_DURATION_STANDARD_RANGE_DAYS": [2, 4],
  "AUCTION_DURATION_LONG_RANGE_DAYS": [7, 10],
  "AUCTION_DURATION_FLASH_DAYS": 1,
  "AUCTION_FLASH_CHANCE": 0.08,
  "AUCTION_LONG_CHANCE_UNCOMMON_RARE": 0.25,
  "AUCTION_TRAVEL_FEE_YEN": {
    "local-yard": 8000,
    "regional": 15000,
    "premium": 25000,
    "collector-network": 40000
  },
  "AUCTION_BUYOUT_PREMIUM": 1.25,
  "AUCTION_WHOLESALE_FRACTION": 0.97,
  "AUCTION_QUIET_DAYS_TO_HAMMER": 3,
  "AUCTION_BID_INCREMENT_FRACTION": 0.05,
  "AUCTION_DAILY_SPAWN_RATE": {
    "local-yard": 0.6,
    "regional": 0.55,
    "premium": 0.4,
    "collector-network": 0.2
  },
  "auctionInterest": {
    "perCohortBidChance": {
      "local-yard": 0.55,
      "regional": 0.5,
      "premium": 0.45,
      "collector-network": 0.4
    },
    "cohortValuationSpreadByTurnout": {
      "thin": 0.3,
      "steady": 0.16,
      "packed": 0.08
    },
    "valueGapEagerBonus": 0.6,
    "valueGapFloor": 0.3,
    "valueGapCeiling": 1.6,
    "turnoutBidderCounts": {
      "thin": [1, 2],
      "steady": [3, 4],
      "packed": [5, 7]
    },
    "turnoutBandWeights": [0.2, 0.45, 0.35],
    "maxIncrementsPerNight": 3
  },
  "restoration": {
    "repairStepFraction": 0.1
  },
  "valuation": {
    "mileageFactorCurve": [
      [30000, 1.05],
      [60000, 1.0],
      [120000, 0.85],
      [180000, 0.75]
    ],
    "marketRepairDiscount": 1.2,
    "partsRetention": 0.55,
    "genuinePeriodMultiplier": 1.25,
    "tasteSpread": 0.12,
    "walkAwaySpread": 0.05,
    "foundation": {
      "parts": [
        "tyres",
        "brakePadsDiscs",
        "brakeCalipersLines",
        "steering",
        "chassis",
        "underbody"
      ],
      "factorByState": {
        "missing": 0.1,
        "scrap": 0.15,
        "poor": 0.45,
        "worn": 1.0,
        "fine": 1.0,
        "mint": 1.0
      }
    }
  },
  "marketPressure": {
    "WAVE_AMPLITUDE": 12,
    "WAVE_PERIOD_WEEKS": 24,
    "SUPPLY_WEIGHT": 4,
    "SALES_WEIGHT": 6,
    "SCARCITY_THRESHOLD": 0.5,
    "SCARCITY_BONUS": 8,
    "HEAT_MIN": 70,
    "HEAT_MAX": 140,
    "SMOOTHING": 0.25,
    "LEDGER_DECAY": 0.75
  },
  "statFormulas": {
    "powerConditionFloor": 0.5,
    "handlingBase": 50,
    "handlingWeightDivisor": 50,
    "styleCap": 20,
    "reliabilityCap": 70,
    "powerNormalizationCeiling": 300
  },
  "bands": {
    "bandFactors": {
      "mint": 1.0,
      "fine": 0.85,
      "worn": 0.65,
      "poor": 0.4,
      "scrap": 0.15
    },
    "migrationThresholds": {
      "mint": 90,
      "fine": 70,
      "worn": 40,
      "poor": 15
    },
    "scrapValueFraction": 0.05
  },
  "partsGeneration": {
    "missingSlotBaseChance": 0.015,
    "missingSlotWeightByPart": {
      "block": 0,
      "internals": 1,
      "headValvetrain": 1,
      "camsTiming": 1,
      "intake": 1,
      "exhaust": 3,
      "fuelSystem": 1,
      "ignitionEcu": 1,
      "cooling": 1,
      "forcedInduction": 0,
      "gearbox": 1,
      "clutch": 1,
      "differential": 1,
      "driveline": 1,
      "chassis": 0,
      "dampers": 1,
      "springs": 1,
      "antiRollBars": 1,
      "steering": 1,
      "brakePadsDiscs": 1,
      "brakeCalipersLines": 1,
      "rims": 3,
      "tyres": 3,
      "panels": 1,
      "paint": 1,
      "underbody": 1,
      "aero": 3,
      "seats": 3,
      "dashGauges": 1
    },
    "mileageRangeMinByAgeYears": [
      [0, 0],
      [1, 1000],
      [2, 5000],
      [4, 12000],
      [8, 35000],
      [12, 55000],
      [20, 90000]
    ],
    "mileageRangeMaxByAgeYears": [
      [0, 3000],
      [1, 12000],
      [2, 30000],
      [4, 55000],
      [8, 105000],
      [12, 150000],
      [20, 230000]
    ],
    "conditionBaselineMinByMileageKm": [
      [0, 70],
      [20000, 58],
      [60000, 45],
      [120000, 33],
      [200000, 22]
    ],
    "conditionBaselineMaxByMileageKm": [
      [0, 98],
      [20000, 95],
      [60000, 88],
      [120000, 78],
      [200000, 68]
    ],
    "upkeepTierWeights": {
      "neglected": 0.25,
      "average": 0.5,
      "cherished": 0.25
    },
    "upkeepBaselineOffset": {
      "neglected": -22,
      "average": 0,
      "cherished": 12
    },
    "upkeepJitterRange": {
      "neglected": [-30, 10],
      "average": [-15, 15],
      "cherished": [-8, 15]
    },
    "upkeepMissingMultiplier": {
      "neglected": 3,
      "average": 1,
      "cherished": 0
    },
    "maxBillFraction": 0.7
  },
  "reputation": {
    "cleanSaleMinBand": "fine",
    "cleanSaleBonus": 2,
    "concoursSaleMinAuthenticityPercent": 85,
    "concoursSaleBonus": 4
  },
  "serviceJobs": {
    "marginMin": 1.18,
    "marginMax": 1.35,
    "laborRateYen": 6000,
    "calloutFeeYen": 5000,
    "dailyOfferCountWeights": [0.05, 0.22, 0.42, 0.23, 0.08],
    "offerCountCapByDay": [
      [1, 1],
      [4, 2],
      [8, 3],
      [12, 99]
    ]
  },
  "selling": {
    "offerChanceBase": 0.65,
    "offerChanceByTier": {
      "shitbox": 1.1,
      "common": 1.05,
      "uncommon": 0.9,
      "rare": 0.75,
      "gaisha": 0.6,
      "legend": 0.45
    },
    "heatBandColdBelowPercent": 90,
    "heatBandHotAtOrAbovePercent": 110,
    "offerChanceByHeatBand": {
      "cold": 0.75,
      "normal": 1.0,
      "hot": 1.3
    },
    "offerSpread": [0.93, 1.05]
  },
  "toolCeilings": {
    "naToTurboConversionEngineTier": 3
  },
  "specialty": {
    "biasFactor": 0.5,
    "softcapPoints": 100,
    "premiumThresholdPoints": 40,
    "inLanePremium": 1.15,
    "titleThresholdPoints": 80,
    "titleBiasMultiplier": 1.25
  },
  "machineListings": {
    "minGapDays": 4,
    "maxGapDays": 8,
    "windowDays": 3
  },
  "coherence": {
    "maxConsumablesShareOfBookValue": 0.15
  }
}
